{
	"name": "SATStore",
	"properties": {
		"linkedServiceName": {
			"referenceName": "AzureSqlDatabase1",
			"type": "LinkedServiceReference"
		},
		"annotations": [],
		"type": "AzureSqlTable",
		"schema": [
			{
				"name": "HK_STORE_ID",
				"type": "varbinary"
			},
			{
				"name": "LOAD_DTS",
				"type": "datetime",
				"precision": 23,
				"scale": 3
			},
			{
				"name": "STORE_NAME",
				"type": "varchar"
			},
			{
				"name": "NUMBER_EMPLOYEES",
				"type": "int",
				"precision": 10
			},
			{
				"name": "WORKING_HOURS",
				"type": "varchar"
			},
			{
				"name": "MANAGER_NAME",
				"type": "varchar"
			},
			{
				"name": "STREET_NUMBER",
				"type": "varchar"
			},
			{
				"name": "STREET_NAME",
				"type": "varchar"
			},
			{
				"name": "CITY",
				"type": "varchar"
			},
			{
				"name": "COUNTY",
				"type": "varchar"
			},
			{
				"name": "STATE",
				"type": "varchar"
			},
			{
				"name": "ZIP",
				"type": "varchar"
			},
			{
				"name": "COUNTRY",
				"type": "varchar"
			},
			{
				"name": "REC_SRC",
				"type": "varchar"
			}
		],
		"typeProperties": {
			"schema": "dbo",
			"table": "SAT_STORE"
		}
	},
	"type": "Microsoft.DataFactory/factories/datasets"
}